pixiedust_twitterdemo/__init__.py
pixiedust_twitterdemo/twitterDemo.py
pixiedust_twitterdemo/templates/demo.html
pixiedust_twitterdemo/templates/demoGroupedChart.js
pixiedust_twitterdemo/templates/demoPieChart.js
pixiedust_twitterdemo/templates/demoScript.html
pixiedust_twitterdemo/templates/startStreaming.execute
stem_ladiespixiedust_twitterdemo-0.2.2.dist-info/DESCRIPTION.rst
stem_ladiespixiedust_twitterdemo-0.2.2.dist-info/METADATA
stem_ladiespixiedust_twitterdemo-0.2.2.dist-info/RECORD
stem_ladiespixiedust_twitterdemo-0.2.2.dist-info/WHEEL
stem_ladiespixiedust_twitterdemo-0.2.2.dist-info/metadata.json
stem_ladiespixiedust_twitterdemo-0.2.2.dist-info/top_level.txt
