Metadata-Version: 2.0
Name: stem-ladiespixiedust-twitterdemo
Version: 0.2.2
Summary: Pixiedust demo of the Twitter Sentiment Analysis tutorialsfor the STEM activity wall
Home-page: https://github.com/lgellis/STEM-twitter-wall/tree/master/twitterdemo
Author: David Taieb the genius and slightly hacked by STEM Women
Author-email: david_taieb@us.ibm.com
License: Apache 2.0
Platform: UNKNOWN
Requires-Dist: pixiedust
